{
	"simulation" : 
	{
		"description" : "Network of 2000 neurons without background input, stimulated with a single pulse to evoke one spike in neuron #1615",
		"short_description" : "defaultnet",
		"runtime" : 25,
		"dt" : 0.2,
		"output_period" : 1,
		"learn_protocol": {
			"time_start": 0,
			"scheme": "EXPLICIT",
			"freq": 0,
			"explicit_input" : {
				"receivers" : [ 1615 ],
				"stim_times" : [ 100 ]
			}
		},
		"recall_protocol": {
			"time_start": 20,
			"scheme": "",
			"freq": 0,
			"N_stim" : 0
		},
		"bg_protocol": {
			"time_start": 0,
			"scheme": "",
			"I_0" : 0,
			"sigma_WN" : 0
		},
		"sample_neuron_ids": [17,1615,1690],
		"sample_synapse_ids": []
	},
	"populations" :
	{
		"N_exc" : 1600,
		"N_inh" : 400,
		"N_CA" : 150,
		"w_ei" : 2.0, 
		"w_ie" : 4.0,
		"w_ii" : 4.0,
		"p_c" : 0.1,
		"p_r" : 0.5,
		"conn_file": "connections_default.txt"
	},
	"neuron" : 
	{
		"mechanism" : "lif",
		"V_init" : -65.0,
		"V_rev" : -65.0,
		"V_reset" : -70.0,
		"V_th" : -55.0,
		"R_leak" : 10.0,
		"R_reset" : 1e-10,
		"C_mem" : 1e-9,
		"t_ref" : 2.0
	},
	"synapses" : 
	{
		"tau_syn" : 5.0,
		"t_ax_delay" : 3.0,
		"syn_exc_calcium_plasticity" : 
		{
			"h_0" : 4.20075,
			"t_Ca_delay" : 18.8,
			"Ca_pre" : 0.6,
			"Ca_post" : 0.1655,
            "sigma_pl" : 2.90436,
			"theta_p" : 3.0,
			"theta_d" : 1.2,
			"theta_pro" : 2.10037,
			"theta_tag" : 0.840149
		}
	}
}

